pypusu/__init__.py
pypusu/base.py
pypusu/errors.py
pypusu/polling.py
pypusu/threaded.py
pypusu-1.0.6.dist-info/LICENSE.md
pypusu-1.0.6.dist-info/METADATA
pypusu-1.0.6.dist-info/WHEEL
pypusu-1.0.6.dist-info/top_level.txt
pypusu-1.0.6.dist-info/RECORD
