Metadata-Version: 2.1
Name: pypusu
Version: 1.0.6
Summary: Python client for PuSuEngine
Home-page: https://github.com/PuSuEngine/pypusu
Author: Janne Enberg
Author-email: janne.enberg@lietu.net
License: UNKNOWN
Download-URL: https://github.com/PuSuEngine/pypusu/tarball/v1.0.6
Keywords: pubsub,publisher,subscriber,messaging
Platform: UNKNOWN
Classifier: Development Status :: 5 - Production/Stable
Classifier: Intended Audience :: Developers
Classifier: License :: OSI Approved
Classifier: Programming Language :: Python
Classifier: Topic :: Communications :: Chat
Classifier: Topic :: Internet :: WWW/HTTP :: Dynamic Content
Classifier: Topic :: Software Development :: Libraries :: Python Modules
Classifier: Programming Language :: Python :: 2
Classifier: Programming Language :: Python :: 2.7
Classifier: Programming Language :: Python :: 3
Classifier: Programming Language :: Python :: 3.6
Classifier: Programming Language :: Python :: 3.7
Requires-Python: >=2.7, !=3.0.*, !=3.1.*, !=3.2.*, !=3.3.*, !=3.4.*,<4
